{"objectType":"Observation","objectVersion":1,"cdwId":"9219924:L","status":"final","category":"laboratory","code":{"coding":{"system":"http://loinc.org","code":"94760-6","display":"COVID-19 (SARS-CoV-2)"}},"subject":{"type":"Patient","reference":"9000756","display":"Mr. Derrick232 Greenfelder433"},"effectiveDateTime":"2020-08-30T20:51:01Z","issued":"2020-09-01T00:35:43Z","performer":[{"type":"Organization","reference":"645083:I","display":"LOMA LINDA HCS"}],"valueCodeableConcept":{"text":"Not Detected"},"specimen":{"type":"Specimen","reference":"1200145681","display":"NASOPHARYNX"}}